odoo/addons/hr_employee_ppe/README.rst
odoo/addons/hr_employee_ppe/__init__.py
odoo/addons/hr_employee_ppe/__manifest__.py
odoo/addons/hr_employee_ppe/data/hr_employee_ppe_cron.xml
odoo/addons/hr_employee_ppe/i18n/es.po
odoo/addons/hr_employee_ppe/i18n/hr_employee_ppe.pot
odoo/addons/hr_employee_ppe/i18n/it.po
odoo/addons/hr_employee_ppe/i18n/pt_BR.po
odoo/addons/hr_employee_ppe/migrations/13.0.2.0.0/post-migration.py
odoo/addons/hr_employee_ppe/models/__init__.py
odoo/addons/hr_employee_ppe/models/hr_personal_equipment.py
odoo/addons/hr_employee_ppe/models/hr_personal_equipment_request.py
odoo/addons/hr_employee_ppe/models/product_template.py
odoo/addons/hr_employee_ppe/readme/CONTRIBUTORS.rst
odoo/addons/hr_employee_ppe/readme/CREDITS.rst
odoo/addons/hr_employee_ppe/readme/DESCRIPTION.rst
odoo/addons/hr_employee_ppe/readme/INSTALL.rst
odoo/addons/hr_employee_ppe/readme/USAGE.rst
odoo/addons/hr_employee_ppe/reports/hr_employee_ppe_report.xml
odoo/addons/hr_employee_ppe/reports/hr_employee_ppe_report_template.xml
odoo/addons/hr_employee_ppe/static/description/banner.png
odoo/addons/hr_employee_ppe/static/description/icon.png
odoo/addons/hr_employee_ppe/static/description/index.html
odoo/addons/hr_employee_ppe/tests/__init__.py
odoo/addons/hr_employee_ppe/tests/test_hr_employee_ppe.py
odoo/addons/hr_employee_ppe/views/hr_personal_equipment.xml
odoo/addons/hr_employee_ppe/views/hr_personal_equipment_request.xml
odoo/addons/hr_employee_ppe/views/product_template.xml
odoo13_addon_hr_employee_ppe-13.0.2.0.1.dev12.dist-info/METADATA
odoo13_addon_hr_employee_ppe-13.0.2.0.1.dev12.dist-info/WHEEL
odoo13_addon_hr_employee_ppe-13.0.2.0.1.dev12.dist-info/top_level.txt
odoo13_addon_hr_employee_ppe-13.0.2.0.1.dev12.dist-info/RECORD
